palaestrai_mosaik/__init__.py
palaestrai_mosaik/config.py
palaestrai_mosaik/mosaik_environment.py
palaestrai_mosaik/simulator.py
palaestrai_mosaik/util.py
palaestrai_mosaik/mp/__init__.py
palaestrai_mosaik/mp/mosaik_environment.py
palaestrai_mosaik/mp/simulator.py
palaestrai_mosaik-3.5.7.dist-info/licenses/LICENSE
palaestrai_mosaik-3.5.7.dist-info/METADATA
palaestrai_mosaik-3.5.7.dist-info/WHEEL
palaestrai_mosaik-3.5.7.dist-info/top_level.txt
palaestrai_mosaik-3.5.7.dist-info/RECORD
