Metadata-Version: 2.4
Name: palaestrai_mosaik
Version: 3.5.7
Summary: Mosaik Environment for palaestrAI.
Author-email: The ARL Developers <stephan.balduin@offis.de>
Project-URL: Homepage, http://docs.palaestr.ai
Project-URL: Bug Tracker, https://gitlab.com/arl2/palaestrai-mosaik/-/issues
Classifier: Development Status :: 4 - Beta
Classifier: Intended Audience :: Science/Research
Classifier: License :: OSI Approved :: GNU Lesser General Public License v2 (LGPLv2)
Classifier: Natural Language :: English
Classifier: Operating System :: POSIX :: Linux
Classifier: Programming Language :: Python
Classifier: Programming Language :: Python :: 3
Classifier: Programming Language :: Python :: 3.10
Classifier: Topic :: Scientific/Engineering
Classifier: Topic :: Scientific/Engineering :: Artificial Intelligence
Requires-Python: >=3.8
License-File: LICENSE
Requires-Dist: midas-mosaik>=2.0.2
Requires-Dist: midas-palaestrai>=3.5.6.post1
Requires-Dist: mosaik>=3.4.0
Requires-Dist: mosaik-api
Requires-Dist: palaestrai>=3.5.6
Provides-Extra: dev
Requires-Dist: black; extra == "dev"
Requires-Dist: build; extra == "dev"
Requires-Dist: coverage; extra == "dev"
Requires-Dist: pytest; extra == "dev"
Requires-Dist: setuptools; extra == "dev"
Requires-Dist: sphinx; extra == "dev"
Requires-Dist: twine; extra == "dev"
Dynamic: license-file
